desktop_helper/__init__.py
desktop_helper/helper.py
desktop_helper/random_example.py
desktop_helper/remove_settings.py
desktop_helper-0.1.1.dist-info/METADATA
desktop_helper-0.1.1.dist-info/WHEEL
desktop_helper-0.1.1.dist-info/licenses/LICENSE
desktop_helper-0.1.1.dist-info/RECORD
