Metadata-Version: 2.1
Name: desktop-helper
Version: 0.1.1
Summary: A simple desktop helper for various kinds of tedious jobs on your desktop.
Project-URL: Homepage, https://github.com/BARaphael/desktop-helper
Project-URL: Bug Tracker, https://github.com/BARaphael/desktop-helper/issues
Author-email: Haonan Lin <zflinhaonan@gmail.com>
License-File: LICENSE
Classifier: License :: OSI Approved :: GNU General Public License v3 (GPLv3)
Classifier: Operating System :: Microsoft :: Windows
Classifier: Programming Language :: Python :: 3
Requires-Python: >=3.7
Requires-Dist: pyqt6>=6.4.0
